-- BYTECODE -- test07.lua:0-37
0001    KSHORT   0   1
0002    KSHORT   1   2
0003    KSHORT   2   3
0004    ADDVV    3   0   1
0005    ADDVV    3   3   2
0006    MULVV    4   1   2
0007    SUBVV    4   0   4
0008    ADDVV    5   1   2
0009    MULVV    5   0   5
0010    ADDVV    6   0   1
0011    ADDVV    7   1   2
0012    MULVV    6   6   7
0013    MODVV    7   0   1
0014    MODVV    8   1   2
0015    DIVVV    7   7   8
0016    GGET     8   0      ; "print"
0017    MOV      9   0
0018    CALL     8   1   2
0019    GGET     8   0      ; "print"
0020    MOV      9   1
0021    CALL     8   1   2
0022    GGET     8   0      ; "print"
0023    MOV      9   2
0024    CALL     8   1   2
0025    GGET     8   0      ; "print"
0026    MOV      9   3
0027    CALL     8   1   2
0028    GGET     8   0      ; "print"
0029    MOV      9   4
0030    CALL     8   1   2
0031    GGET     8   0      ; "print"
0032    MOV      9   5
0033    CALL     8   1   2
0034    GGET     8   0      ; "print"
0035    MOV      9   6
0036    CALL     8   1   2
0037    GGET     8   0      ; "print"
0038    MOV      9   7
0039    CALL     8   1   2
0040    RET0     0   1

