---- TRACE 1 start test50.lua:18
0009  KSHORT   8 100
0010  ISGE     8   7
0011  JMP      8 => 0013
0013  KSHORT   8 200
0014  ISGE     8   7
0015  JMP      8 => 0017
0017  KSHORT   8 300
0018  ISGE     8   7
0019  JMP      8 => 0021
0021  FORL     4 => 0009
---- TRACE 1 IR
0001    int SLOAD  #5    I
0002 >  int LE     0001  +100
0003 >  int LE     0001  +200
0004 >  int LE     0001  +300
0005  + int ADD    0001  +1  
0006 >  int LE     0005  +1000
0007 ------ LOOP ------------
0008 >  int LE     0005  +100
0009 >  int LE     0005  +200
0010 >  int LE     0005  +300
0011  + int ADD    0005  +1  
0012 >  int LE     0011  +1000
0013    int PHI    0005  0011
---- TRACE 1 stop -> loop

---- TRACE 2 start 1/1 test50.lua:20
0012  ADDVN    1   1   0  ; 1
0013  KSHORT   8 200
0014  ISGE     8   7
0015  JMP      8 => 0017
0017  KSHORT   8 300
0018  ISGE     8   7
0019  JMP      8 => 0021
0021  JFORL    4   1
---- TRACE 2 IR
0001    int SLOAD  #5    PI
0002 >  int SLOAD  #2    T
0003 >  int ADDOV  0002  +1  
0004 >  int LE     0001  +200
0005 >  int LE     0001  +300
0006    int ADD    0001  +1  
0007 >  int LE     0006  +1000
---- TRACE 2 stop -> 1

---- TRACE 3 start 2/1 test50.lua:23
0016  ADDVN    2   2   0  ; 1
0017  KSHORT   8 300
0018  ISGE     8   7
0019  JMP      8 => 0021
0021  JFORL    4   1
---- TRACE 3 IR
0001    int SLOAD  #2    PI
0002    int SLOAD  #5    PI
0003 >  int SLOAD  #3    T
0004 >  int ADDOV  0003  +1  
0005 >  int LE     0002  +300
0006    int ADD    0002  +1  
0007 >  int LE     0006  +1000
---- TRACE 3 stop -> 1

---- TRACE 4 start 3/1 test50.lua:26
0020  ADDVN    3   3   0  ; 1
0021  JFORL    4   1
---- TRACE 4 IR
0001    int SLOAD  #2    PI
0002    int SLOAD  #3    PI
0003    int SLOAD  #5    PI
0004 >  int SLOAD  #4    T
0005 >  int ADDOV  0004  +1  
0006    int ADD    0003  +1  
0007 >  int LE     0006  +1000
---- TRACE 4 stop -> 1

